pytijo/__init__.py
pytijo/constants.py
pytijo/parser.py
pytijo/modules/__init__.py
pytijo/modules/tijo_re.py
pytijo-0.0.2.dist-info/LICENSE.txt
pytijo-0.0.2.dist-info/METADATA
pytijo-0.0.2.dist-info/WHEEL
pytijo-0.0.2.dist-info/top_level.txt
pytijo-0.0.2.dist-info/RECORD
